scryp/__init__.py
scrypt/__init__.py
scryp-0.0.5.dist-info/LICENSE
scryp-0.0.5.dist-info/METADATA
scryp-0.0.5.dist-info/WHEEL
scryp-0.0.5.dist-info/top_level.txt
scryp-0.0.5.dist-info/RECORD
