Metadata-Version: 2.1
Name: scryp
Version: 0.0.5
Summary: A Simple String Encryption Tool.
Home-page: https://github.com/shivjeetbhullar/scrypt
Author: Shivjeet Singh Bhullar
Author-email: bhullarshivjeet@gmail.com
License: UNKNOWN
Platform: UNKNOWN
Classifier: Programming Language :: Python :: 3
Classifier: License :: OSI Approved :: GNU General Public License v3 or later (GPLv3+)
Classifier: Operating System :: OS Independent
Classifier: Topic :: Database
Requires-Python: >=3
